{
  "markdown": "# Not Found\n\nThe requested URL was not found on this server.\n\n* * *\n\nApache Server at lists.debian.org Port 443",
  "metadata": {
    "title": "404 Not Found",
    "scrapeId": "6cb5c598-ccfd-47d2-a7a2-ba639f20c1fd",
    "sourceURL": "https://lists.debian.org/debian-qwertasdfzxcv123456789xyz/",
    "url": "https://lists.debian.org/debian-qwertasdfzxcv123456789xyz/",
    "statusCode": 404,
    "error": "Not Found",
    "contentType": "text/html; charset=iso-8859-1",
    "proxyUsed": "basic",
    "creditsUsed": 1,
    "scrapedAt": "2025-08-12T04:00:33.039445"
  },
  "success": true,
  "cached_at": "2025-08-12T04:00:33.039478",
  "url": "https://lists.debian.org/debian-qwertasdfzxcv123456789xyz/"
}