{
  "markdown": "# 404\n\nSorry, we can't find the page you're looking for.\n\n[Go Back Home](https://clearbit.com/) [or Explore Clearbit](https://clearbit.com/resources/tools/explore-clearbit)",
  "metadata": {
    "favicon": "https://clearbit.com/favicon-192.png",
    "ogUrl": "/404",
    "og:title": "404",
    "og:type": "website",
    "og:image:alt": "404",
    "og:url": "/404",
    "language": "en",
    "og:image:width": "1200",
    "og:image": "/sharing/social-share-2.jpg",
    "og:image:height": "630",
    "next-head-count": "14",
    "og:description": "Page not found",
    "description": "Page not found",
    "ogDescription": "Page not found",
    "title": "404",
    "robots": "noindex,follow",
    "ogTitle": "404",
    "viewport": "width=device-width, initial-scale=1.0",
    "ogImage": "/sharing/social-share-2.jpg",
    "scrapeId": "69d6628e-4ae2-4925-9cf3-c682340edd15",
    "sourceURL": "https://clearbit.com/companies/qwertasdfzxcv123456789xyz",
    "url": "https://clearbit.com/companies/qwertasdfzxcv123456789xyz",
    "statusCode": 404,
    "error": "Not Found",
    "contentType": "text/html; charset=utf-8",
    "proxyUsed": "basic",
    "creditsUsed": 1,
    "scrapedAt": "2025-08-12T03:47:08.559355"
  },
  "success": true,
  "cached_at": "2025-08-12T03:47:08.559401",
  "url": "https://clearbit.com/companies/qwertasdfzxcv123456789xyz"
}