{
  "generated_at": "2025-12-21T19:20:59.826Z",
  "description": "Legacy jurisdiction codes/names → ISO-3166-1 alpha-2 (derived during matrix build)",
  "cctld_overrides": {
    "uk": "GB"
  },
  "default_by_legacy_key": {
    "AL": "AL",
    "AR": "AR",
    "AU": "AT",
    "AZ": "AZ",
    "BA": "BD",
    "BE": "BE",
    "BO": "BO",
    "BR": "BR",
    "BU": "BG",
    "CA": "CA",
    "CH": "CL",
    "CO": "CO",
    "CR": "HR",
    "CY": "CY",
    "CZ": "CZ",
    "DE": "DK",
    "EC": "EC",
    "EG": "EG",
    "ES": "EE",
    "FI": "FI",
    "FR": "FR",
    "GE": "DE",
    "GLOBAL": "IO",
    "GR": "GR",
    "HU": "HU",
    "IC": "IS",
    "ID": "ID",
    "IN": "IN",
    "IR": "IE",
    "IS": "IL",
    "IT": "IT",
    "JA": "JP",
    "KA": "KZ",
    "KE": "KE",
    "LA": "LV",
    "LI": "LT",
    "LU": "LU",
    "MA": "MY",
    "ME": "MX",
    "MO": "ME",
    "NE": "NL",
    "NI": "NG",
    "NO": "NO",
    "PA": "PY",
    "PE": "PE",
    "PH": "PH",
    "PO": "PL",
    "RO": "RO",
    "RU": "RU",
    "SA": "SA",
    "SE": "RS",
    "SI": "SG",
    "SL": "SK",
    "SO": "ZA",
    "SP": "ES",
    "SW": "CH",
    "TA": "TW",
    "TH": "TH",
    "TR": "TT",
    "TU": "TR",
    "UA": "UA",
    "UK": "GB",
    "UR": "UY",
    "US": "GB",
    "VE": "VE",
    "VI": "VN"
  },
  "region_name_examples": {
    "United Kingdom": "GB",
    "United States": "US",
    "Czech Republic": "CZ",
    "Ivory Coast": "CI",
    "Viet Nam": "VN"
  }
}
